aeroet/__init__.py
aeroet/air.py
aeroet/model.py
aeroet/radiation.py
aeroet/surface.py
aeroet/utils.py
aeroet/uncertainty/__init__.py
aeroet/uncertainty/atmosphere.py
aeroet/uncertainty/partials.py
aeroet/uncertainty/resistance.py
aeroet/uncertainty/temperature.py
aeroet/uncertainty/utils.py
aeroet-0.1.1.dist-info/LICENSE
aeroet-0.1.1.dist-info/METADATA
aeroet-0.1.1.dist-info/WHEEL
aeroet-0.1.1.dist-info/top_level.txt
aeroet-0.1.1.dist-info/RECORD
