Metadata-Version: 2.1
Name: aeroet
Version: 0.1.1
Summary: Surface energy balance and atmospheric profiling algorithms for calculating evapotranspiration from thermal imagery
Author-email: Bryn Morgan <brynmorgan@ucsb.edu>
License: GNU GENERAL PUBLIC LICENSE
Project-URL: homepage, https://github.com/brynemorgan/aeroet
Keywords: uav,evapotranspiration,thermal imaging,drones,ecohydrology
Classifier: Programming Language :: Python
Classifier: Programming Language :: Python :: 3
Requires-Python: >=3.10
License-File: LICENSE
Requires-Dist: numpy
Requires-Dist: pandas
Requires-Dist: xarray
